nonebot_plugin_uma-0.1.0.dev2.dist-info/METADATA
nonebot_plugin_uma-0.1.0.dev2.dist-info/WHEEL
nonebot_plugin_uma-0.1.0.dev2.dist-info/licenses/LICENSE
nonebot_plugin_uma/__init__.py
nonebot_plugin_uma/__main__.py
nonebot_plugin_uma/config.py
nonebot_plugin_uma/resource.py
nonebot_plugin_uma/uma_skills/__init__.py
nonebot_plugin_uma/uma_skills/data_source.py
nonebot_plugin_uma/uma_skills/generate.py
nonebot_plugin_uma/uma_skills/res/uma_skills_help.png
nonebot_plugin_uma/uma_skills/update.py
nonebot_plugin_uma/utils.py
nonebot_plugin_uma-0.1.0.dev2.dist-info/RECORD
