Metadata-Version: 2.1
Name: nonebot-plugin-uma
Version: 0.1.0.dev2
Summary: A ported version of azmiao/uma_plugin for NoneBot2.
Home-page: https://github.com/lgc-NB2Dev/nonebot-plugin-uma
Author-Email: Perseus037 <1209228678@qq.com>, student_2333 <lgc2333@126.com>
License: MIT
Project-URL: Homepage, https://github.com/lgc-NB2Dev/nonebot-plugin-uma
Requires-Python: <4.0,>=3.8
Requires-Dist: nonebot2>=2.1.0
Requires-Dist: nonebot-adapter-onebot>=2.2.0
Requires-Dist: nonebot-plugin-apscheduler>=0.3.0
Requires-Dist: nonebot-plugin-htmlrender>=0.2.2
Requires-Dist: pydantic<2,>=1.10.4
Requires-Dist: httpx>=0.25.0
Requires-Dist: lxml>=4.9.3
Requires-Dist: beautifulsoup4>=4.12.2
Requires-Dist: pillow<10
Requires-Dist: fuzzywuzzy>=0.18.0
Requires-Dist: pil-utils>=0.1.8
